wheeldiff/__init__.py
wheeldiff/_impl/__init__.py
wheeldiff/_impl/cmd.py
wheeldiff-2025.8.dist-info/licenses/LICENSE
wheeldiff-2025.8.dist-info/METADATA
wheeldiff-2025.8.dist-info/WHEEL
wheeldiff-2025.8.dist-info/entry_points.txt
wheeldiff-2025.8.dist-info/top_level.txt
wheeldiff-2025.8.dist-info/RECORD
