Metadata-Version: 2.4
Name: wheeldiff
Version: 2025.8
Summary: Diff two Python wheels
Author-email: Rohan McGovern <rohan@mcgovern.id.au>
Maintainer-email: Rohan McGovern <rohan@mcgovern.id.au>
License:                     GNU GENERAL PUBLIC LICENSE
Project-URL: homepage, https://github.com/rohanpm/wheeldiff
Requires-Python: >=3.8
License-File: LICENSE
Requires-Dist: wheel
Requires-Dist: wheel-filename
Dynamic: license-file
